mintpy/__init__.py
mintpy/__main__.py
mintpy/add.py
mintpy/asc_desc2horz_vert.py
mintpy/closure_phase_bias.py
mintpy/constants.py
mintpy/dem_error.py
mintpy/dem_gsi.py
mintpy/diff.py
mintpy/generate_mask.py
mintpy/geocode.py
mintpy/ifgram_inversion.py
mintpy/image_math.py
mintpy/image_stitch.py
mintpy/info.py
mintpy/iono_split_spectrum.py
mintpy/iono_tec.py
mintpy/load_data.py
mintpy/load_gbis.py
mintpy/local_oscilator_drift.py
mintpy/lookup_geo2radar.py
mintpy/mask.py
mintpy/modify_network.py
mintpy/multi_transect.py
mintpy/multilook.py
mintpy/plate_motion.py
mintpy/plot_coherence_matrix.py
mintpy/plot_network.py
mintpy/plot_transection.py
mintpy/prep_aria.py
mintpy/prep_cosicorr.py
mintpy/prep_fringe.py
mintpy/prep_gamma.py
mintpy/prep_gmtsar.py
mintpy/prep_hyp3.py
mintpy/prep_isce.py
mintpy/prep_nisar.py
mintpy/prep_roipac.py
mintpy/reference_date.py
mintpy/reference_point.py
mintpy/s1ab_range_bias.py
mintpy/save_explorer.py
mintpy/save_gbis.py
mintpy/save_gdal.py
mintpy/save_gmt.py
mintpy/save_hdfeos5.py
mintpy/save_kite.py
mintpy/save_kmz.py
mintpy/save_kmz_timeseries.py
mintpy/save_qgis.py
mintpy/save_roipac.py
mintpy/smallbaselineApp.py
mintpy/solid_earth_tides.py
mintpy/spatial_filter.py
mintpy/subset.py
mintpy/timeseries2velocity.py
mintpy/timeseries_rms.py
mintpy/tropo_gacos.py
mintpy/tropo_phase_elevation.py
mintpy/tropo_pyaps3.py
mintpy/tsview.py
mintpy/unwrap_error_bridging.py
mintpy/unwrap_error_phase_closure.py
mintpy/version.py
mintpy/view.py
mintpy/cli/__init__.py
mintpy/cli/add.py
mintpy/cli/asc_desc2horz_vert.py
mintpy/cli/closure_phase_bias.py
mintpy/cli/dem_error.py
mintpy/cli/dem_gsi.py
mintpy/cli/diff.py
mintpy/cli/generate_mask.py
mintpy/cli/geocode.py
mintpy/cli/ifgram_inversion.py
mintpy/cli/image_math.py
mintpy/cli/image_stitch.py
mintpy/cli/info.py
mintpy/cli/iono_split_spectrum.py
mintpy/cli/iono_tec.py
mintpy/cli/load_data.py
mintpy/cli/load_gbis.py
mintpy/cli/local_oscilator_drift.py
mintpy/cli/lookup_geo2radar.py
mintpy/cli/mask.py
mintpy-1.6.2.dist-info/licenses/LICENSE
mintpy-1.6.2.dist-info/METADATA
mintpy-1.6.2.dist-info/WHEEL
mintpy-1.6.2.dist-info/entry_points.txt
mintpy-1.6.2.dist-info/top_level.txt
mintpy-1.6.2.dist-info/RECORD
